webparsa/__init__.py
webparsa/dicttools.py
webparsa/functions.py
webparsa/getters.py
webparsa/matches.py
webparsa/messages.py
webparsa/nodes.py
webparsa/webparsa.py
webparsa-0.0.2.dist-info/LICENSE
webparsa-0.0.2.dist-info/METADATA
webparsa-0.0.2.dist-info/WHEEL
webparsa-0.0.2.dist-info/top_level.txt
webparsa-0.0.2.dist-info/RECORD
