Metadata-Version: 2.1
Name: webparsa
Version: 0.0.2
Summary: This project uses XML templates to extract data from websites for you, with almost no code
Home-page: https://github.com/myfatemi04/webparsa
Author: Michael Fatemi
Author-email: myfatemi04@gmail.com
License: UNKNOWN
Platform: UNKNOWN
Classifier: Programming Language :: Python :: 3
Classifier: License :: OSI Approved :: MIT License
Classifier: Operating System :: OS Independent
Requires-Python: >=3.6
Requires-Dist: beautifulsoup4
Requires-Dist: lxml (>=4.5)
